datasets/__init__.py
datasets/pointcloud.py
datasets/pointcloud_eval.py
datasets/shapenet.py
datasets/shapenet_vae.py
datasets/synthetic_room.py
datasets/utils.py
ognn/__init__.py
ognn/ae.py
ognn/loss.py
ognn/mpu.py
ognn/nn.py
ognn/octreed.py
ognn/ounet.py
ognn/unet.py
ognn/utils.py
ognn/vae.py
ognn-1.1.2.dist-info/LICENSE
ognn-1.1.2.dist-info/METADATA
ognn-1.1.2.dist-info/WHEEL
ognn-1.1.2.dist-info/top_level.txt
ognn-1.1.2.dist-info/RECORD
