Metadata-Version: 2.1
Name: ognn
Version: 1.1.2
Summary: Dual Octree Graph Neural Networks
Home-page: https://github.com/octree-nn/ognn-pytorch
Author: Peng-Shuai Wang
Author-email: wangps@hotmail.com
License: MIT
Classifier: Programming Language :: Python :: 3
Classifier: License :: OSI Approved :: MIT License
Classifier: Operating System :: OS Independent
Requires-Python: >=3.6
License-File: LICENSE
Requires-Dist: torch
Requires-Dist: numpy
Requires-Dist: ocnn
Requires-Dist: easydict
